azc/__init__.py
azc/azc_demo.py
azc_sdk-1.1.2.dist-info/METADATA
azc_sdk-1.1.2.dist-info/WHEEL
azc_sdk-1.1.2.dist-info/top_level.txt
azc_sdk-1.1.2.dist-info/RECORD
